LICENCE
MANIFEST.in
NEWS
README.md
setup.py
Moose.egg-info/PKG-INFO
Moose.egg-info/SOURCES.txt
Moose.egg-info/dependency_links.txt
Moose.egg-info/entry_points.txt
Moose.egg-info/not-zip-safe
Moose.egg-info/requires.txt
Moose.egg-info/top_level.txt
docs/Makefile
docs/api.rst
docs/conf.py
docs/contributing.rst
docs/index.rst
docs/make.bat
docs/news.rst
docs/.static/export-overview.png
docs/.static/upload-overview.png
docs/drafts/Moose Milestone(release:1.0).md
docs/extra/business.rst
docs/intro/examples.rst
docs/intro/install.rst
docs/intro/overview.rst
docs/intro/quickstart.rst
docs/topics/actions.rst
docs/topics/app-templates.rst
docs/topics/commands.rst
docs/topics/connections.rst
docs/topics/drawer.rst
docs/topics/exceptions.rst
docs/topics/models.rst
docs/topics/order.rst
docs/topics/process.rst
docs/topics/settings.rst
moose/.__init__.py.swp
moose/VERSION
moose/__init__.py
moose/shortcuts.py
moose/actions/__init__.py
moose/actions/base.py
moose/actions/export.py
moose/actions/files.py
moose/actions/migrate.py
moose/actions/operate.py
moose/actions/review.py
moose/actions/stats.py
moose/actions/upload.py
moose/actions/uploads.py
moose/apps/__init__.py
moose/apps/config.py
moose/apps/registry.py
moose/bin/moose-admin.py
moose/conf/__init__.py
moose/conf/global_settings.py
moose/conf/app_template/__init__.py
moose/conf/app_template/actions.py-tpl
moose/conf/app_template/apps.py-tpl
moose/conf/app_template/models.py-tpl
moose/conf/app_template/tests.py-tpl
moose/conf/project_template/manage.py-tpl
moose/conf/project_template/project_name/__init__.py
moose/conf/project_template/project_name/settings.py-tpl
moose/conf/project_template/project_name/settings.py-tpl.bak
moose/conf/project_template/project_name/template.cfg-tpl
moose/connection/__init__.py
moose/connection/cloud.py
moose/connection/database.py
moose/connection/fetch.py
moose/connection/mongodb.py
moose/connection/mssql.py
moose/connection/mysql.py
moose/connection/operations.py
moose/connection/query.py
moose/connection/sqlhandler.py
moose/core/__init__.py
moose/core/exceptions.py
moose/core/mail.py
moose/core/terminal.py
moose/core/configs/__init__.py
moose/core/configs/loader.py
